our_planner-0.1.17.dist-info/licenses/LICENSE.txt
src/__init__.py
src/main.py
src/controller/__init__.py
src/controller/task_manager.py
src/model/__init__.py
src/model/task_resource_model.py
src/operations/__init.py
src/operations/export_operations.py
src/operations/file_operations.py
src/operations/network_operations.py
src/operations/tag_operations.py
src/operations/task_operations.py
src/utils/__init__.py
src/utils/colors.py
src/utils/version.py
src/view/__init__.py
src/view/ui_components.py
src/view/dialogs/__init__.py
src/view/menus/__init__.py
src/view/menus/help_menu.py
src/view/menus/network_menu.py
our_planner-0.1.17.dist-info/METADATA
our_planner-0.1.17.dist-info/WHEEL
our_planner-0.1.17.dist-info/entry_points.txt
our_planner-0.1.17.dist-info/top_level.txt
our_planner-0.1.17.dist-info/RECORD
