Metadata-Version: 2.4
Name: our-planner
Version: 0.1.17
Summary: An application for collaboratively working on plans with our team. Planning can take resource availability into account. Timeline visualization for tasks and resources makes it easy to modify and sense check.  Buffer management features provide early indicators that actual and planned activity requires intervention.
Author-email: "R.N. Wolf" <rudi@rnwolf.net>
Maintainer-email: Rüdiger Wolf <rudi@rnwolf.net>
License-Expression: GPL-3.0-or-later
Keywords: planning,resource management,task management,collaboration,visualization,buffer management,teamwork,desktop,cross-platform
Classifier: Programming Language :: Python :: 3
Classifier: Programming Language :: Python :: 3.11
Classifier: Operating System :: OS Independent
Classifier: Intended Audience :: End Users/Desktop
Classifier: Intended Audience :: Information Technology
Classifier: Topic :: Office/Business :: Scheduling
Classifier: Development Status :: 3 - Alpha
Classifier: Environment :: Win32 (MS Windows)
Classifier: Environment :: MacOS X
Classifier: Natural Language :: English
Requires-Python: >=3.11
License-File: LICENSE.txt
Requires-Dist: tkcalendar>=1.6.1
Requires-Dist: reportlab>=4.0.0
Requires-Dist: networkx>=3.0
Requires-Dist: requests>=2.32.3
Dynamic: license-file
